irobot_edu_sdk/__init__.py
irobot_edu_sdk/backend/__init__.py
irobot_edu_sdk/backend/backend.py
irobot_edu_sdk/backend/bluetooth.py
irobot_edu_sdk/backend/bluetooth_desktop.py
irobot_edu_sdk/backend/bluetooth_web.py
irobot_edu_sdk/backend/serial.py
irobot_edu_sdk/backend/turtle.py
irobot_edu_sdk/backend/usb.py
irobot_edu_sdk/color.py
irobot_edu_sdk/completer.py
irobot_edu_sdk/create3.py
irobot_edu_sdk/event.py
irobot_edu_sdk/getter_types.py
irobot_edu_sdk/music.py
irobot_edu_sdk/packet.py
irobot_edu_sdk/robot.py
irobot_edu_sdk/robot_turtle.py
irobot_edu_sdk/robots.py
irobot_edu_sdk/root.py
irobot_edu_sdk/utils.py
irobot_edu_sdk-0.6.0.dist-info/LICENSE.txt
irobot_edu_sdk-0.6.0.dist-info/METADATA
irobot_edu_sdk-0.6.0.dist-info/WHEEL
irobot_edu_sdk-0.6.0.dist-info/RECORD
