Metadata-Version: 2.1
Name: irobot_edu_sdk
Version: 0.6.0
Summary: Python SDK for iRobot Edu robots
Home-page: https://python.irobot.com
License: BSD-3-Clause
Author: iRobot Corporation
Author-email: education@irobot.com
Requires-Python: >=3.9,<4.0
Classifier: Development Status :: 4 - Beta
Classifier: Environment :: Console
Classifier: License :: OSI Approved :: BSD License
Classifier: Operating System :: OS Independent
Classifier: Programming Language :: Python :: 3
Classifier: Programming Language :: Python :: 3.9
Classifier: Programming Language :: Python :: 3.10
Classifier: Programming Language :: Python :: 3.11
Classifier: Programming Language :: Python :: 3.12
Requires-Dist: bleak (>=0.22,<0.23)
Requires-Dist: pyserial (>=3.4,<4.0)
Project-URL: Repository, https://github.com/iRobotEducation/irobot-edu-python-sdk
